LICENSE
MANIFEST.in
README.rst
requirements.txt
setup.py
dials/__init__.py
dials/bibtex.py
dials/constants.py
dials/objects.py
dials/protocols.conf
dials/utils.py
dials/convert/__init__.py
dials/convert/input_output_utils.py
dials/convert/phils_utils.py
dials/protocols/__init__.py
dials/protocols/protocol_dials_base.py
dials/protocols/protocol_dials_import.py
dials/protocols/protocol_export.py
dials/protocols/protocol_find_spots.py
dials/protocols/protocol_index.py
dials/protocols/protocol_integrate.py
dials/protocols/protocol_merge.py
dials/protocols/protocol_refine.py
dials/protocols/protocol_scaling.py
dials/protocols/protocol_symmetry.py
dials/tests/__init__.py
dials/tests/test_ed_dials.py
dials/viewers/__init__.py
dials/viewers/dials_viewer_utils.py
dials/viewers/dials_viewers.py
scipion_ed_dials.egg-info/PKG-INFO
scipion_ed_dials.egg-info/SOURCES.txt
scipion_ed_dials.egg-info/dependency_links.txt
scipion_ed_dials.egg-info/entry_points.txt
scipion_ed_dials.egg-info/requires.txt
scipion_ed_dials.egg-info/top_level.txt