Metadata-Version: 2.1
Name: scipion-ed-dials
Version: 3!1.0.0b4
Summary: Scipion-ED plugin to use programs from DIALS for Electron Diffraction image processing.
Home-page: https://github.com/scipion-ed-dials/scipion-ed-dials
Author: J.M. De la Rosa Trevin, Viktor E. G. Bengtsson
Author-email: delarosatrevin@scilifelab.se, viktor.bengtsson@mmk.su.se
License: UNKNOWN
Project-URL: Bug Reports, https://github.com/scipion-ed-dials/scipion-ed-dials/issues
Project-URL: Source, https://github.com/scipion-ed-dials/scipion-ed-dials/
Keywords: workflows science pyworkflow image-processing scipion electron diffraction
Platform: UNKNOWN
Classifier: Development Status :: 4 - Beta
Classifier: Intended Audience :: Science/Research
Classifier: License :: OSI Approved :: GNU General Public License v3 (GPLv3)
Classifier: Programming Language :: Python :: 3.6
Classifier: Programming Language :: Python :: 3.7
Classifier: Programming Language :: Python :: 3.8
Classifier: Programming Language :: Python :: 3 :: Only
Classifier: Topic :: Scientific/Engineering
License-File: LICENSE
